seg2map/__init__.py
seg2map/common.py
seg2map/downloads.py
seg2map/exception_handler.py
seg2map/exceptions.py
seg2map/log_maker.py
seg2map/map_UI.py
seg2map/map_functions.py
seg2map/map_interface.py
seg2map/model_functions.py
seg2map/models_UI.py
seg2map/new_downloads.py
seg2map/roi.py
seg2map/sessions.py
seg2map/zoo_model.py
seg2map-0.0.14.dist-info/LICENSE
seg2map-0.0.14.dist-info/METADATA
seg2map-0.0.14.dist-info/WHEEL
seg2map-0.0.14.dist-info/top_level.txt
seg2map-0.0.14.dist-info/RECORD
