Metadata-Version: 2.1
Name: seg2map
Version: 0.0.14
Summary: An interactive jupyter notebook for downloading satellite imagery
Author-email: Sharon Fitzpatrick <sharon.fitzpatrick23@gmail.com>
License: MIT License
Project-URL: Homepage, https://github.com/Doodleverse/seg2map
Project-URL: Bug Tracker, https://github.com/Doodleverse/seg2map/issues
Classifier: Programming Language :: Python :: 3
Classifier: License :: OSI Approved :: MIT License
Classifier: Operating System :: OS Independent
Requires-Python: >=3.9
License-File: LICENSE
Requires-Dist: scikit-image
Requires-Dist: imageio
Requires-Dist: transformers
Requires-Dist: rasterio
Requires-Dist: area
Requires-Dist: doodleverse-utils (>=0.0.33)
Requires-Dist: ipyfilechooser (>=0.6.0)
Requires-Dist: tqdm
Requires-Dist: leafmap (>=0.14.0)
Requires-Dist: geemap
Requires-Dist: geojson
Requires-Dist: aiohttp
Requires-Dist: nest-asyncio
Requires-Dist: tensorflow
